<?xml version="1.0" encoding="utf-8" ?>

<root xmlns="http://rsdn.ru/projects/Janus/JanusMenuDescriptor.xsd"
      name="MessageViewer.Toolbar">

  <group name="DeleteRate">
    
    <menuCommand command="Janus.Forum.RateMessage"
                 textResource="MessageViewerRateDelete"
                 image="MessageViewer\RateX">
      <parameter name="rate">DeleteRate</parameter>
    </menuCommand>
  
  </group>

  <group name="BallRate">
  
    <menuCommand command="Janus.Forum.RateMessage"
                 textResource="MessageViewerRatePlus1"
                 image="MessageViewer\RatePlus1">
      <parameter name="rate">Plus1</parameter>
    </menuCommand>
    
    <menuCommand command="Janus.Forum.RateMessage"
                 textResource="MessageViewerRateOne"
                 image="MessageViewer\Rate1">
      <parameter name="rate">Rate1</parameter>
    </menuCommand>
    
    <menuCommand command="Janus.Forum.RateMessage"
                 textResource="MessageViewerRateTwo"
                 image="MessageViewer\Rate2">
      <parameter name="rate">Rate2</parameter>
    </menuCommand>
    
    <menuCommand command="Janus.Forum.RateMessage"
                 textResource="MessageViewerRateThree"
                 image="MessageViewer\Rate3">
      <parameter name="rate">Rate3</parameter>
    </menuCommand>
    
  </group>

  <group name="SmileRate">
    
    <menuCommand command="Janus.Forum.RateMessage"
                 textResource="MessageViewerRateSmile"
                 image="MessageViewer\RateSmile">
      <parameter name="rate">Smile</parameter>
    </menuCommand>
    
  </group>

  <group name="AgreeDisagreeRate">
    
    <menuCommand command="Janus.Forum.RateMessage"
                 textResource="MessageViewerRateAgree"
                 image="MessageViewer\RateAgree">
      <parameter name="rate">Agree</parameter>
    </menuCommand>
    
    <menuCommand command="Janus.Forum.RateMessage"
                 textResource="MessageViewerRateDisagree"
                 image="MessageViewer\RateDisagree">
      <parameter name="rate">DisAgree</parameter>
    </menuCommand>
  
  </group>

  <group name="Moderating">
  
    <menuCommand command="Janus.Forum.Moderating" image="MessageViewer\Moderating"/>
		<menuCommand command="Janus.Forum.WarnModeratorOnRsdn" image="MessageViewer\WarnModerator"/>
  </group>

</root>